cli/__init__.py
cli/mk10.py
cli/commands/__init__.py
cli/commands/execute.py
cli/commands/ingest.py
cli/commands/promote.py
cli/commands/verify.py
engine/__init__.py
engine/core/__init__.py
engine/core/context.py
engine/core/dag.py
engine/core/engine.py
engine/core/errors.py
engine/core/node.py
engine/core/nodes/__init__.py
engine/core/nodes/content_verifier.py
engine/evidence/__init__.py
engine/evidence/canonical.py
engine/evidence/hash.py
engine/evidence/recorder.py
engine/evidence/signatures.py
engine/formats/__init__.py
engine/formats/dcp/__init__.py
engine/formats/dcp/validate.py
engine/policy/__init__.py
engine/policy/policy.py
engine/util/__init__.py
engine/util/fs.py
engine/util/json.py
engine/util/time.py
mk10_pro-1.0.2.dist-info/licenses/LICENSE
mtb/__init__.py
mtb/builder.py
mtb/seal.py
mtb/verify.py
verifier/__init__.py
verifier/seal.py
verifier/verify.py
verifier/verify_mtb.py
verifier/utils/__init__.py
verifier/utils/errors.py
verifier/utils/hash.py
verifier/utils/json.py
mk10_pro-1.0.2.dist-info/METADATA
mk10_pro-1.0.2.dist-info/WHEEL
mk10_pro-1.0.2.dist-info/entry_points.txt
mk10_pro-1.0.2.dist-info/top_level.txt
mk10_pro-1.0.2.dist-info/RECORD
