Metadata-Version: 2.4
Name: mk10-pro
Version: 1.0.2
Summary: Deterministic pre-delivery truth infrastructure for audiovisual mastering. Produces cryptographically verifiable Master Truth Bundles (MTB).
Author-email: kaaffilm <dev@kaaffilm.com>
License-Expression: MIT
Project-URL: Homepage, https://github.com/kaaffilm/MK10-PRO
Project-URL: Repository, https://github.com/kaaffilm/MK10-PRO
Project-URL: Documentation, https://github.com/kaaffilm/MK10-PRO#readme
Project-URL: Changelog, https://github.com/kaaffilm/MK10-PRO/releases
Project-URL: Issues, https://github.com/kaaffilm/MK10-PRO/issues
Keywords: verification,deterministic,audiovisual,mastering,cryptographic,mtb,truth-bundle
Classifier: Development Status :: 4 - Beta
Classifier: Intended Audience :: Developers
Classifier: Intended Audience :: Information Technology
Classifier: Operating System :: OS Independent
Classifier: Programming Language :: Python :: 3
Classifier: Programming Language :: Python :: 3.9
Classifier: Programming Language :: Python :: 3.10
Classifier: Programming Language :: Python :: 3.11
Classifier: Programming Language :: Python :: 3.12
Classifier: Topic :: Security :: Cryptography
Classifier: Topic :: Multimedia :: Video
Classifier: Topic :: Software Development :: Quality Assurance
Classifier: Typing :: Typed
Requires-Python: >=3.9
License-File: LICENSE
Requires-Dist: pyyaml>=6.0
Requires-Dist: click>=8.0
Requires-Dist: jsonschema>=4.0
Requires-Dist: cryptography>=41.0
Requires-Dist: pycryptodome>=3.19.0
Requires-Dist: lxml>=4.9.0
Requires-Dist: xmlschema>=2.0.0
Requires-Dist: python-dateutil>=2.8.0
Requires-Dist: pytz>=2023.3
Provides-Extra: dev
Requires-Dist: pytest>=7.0; extra == "dev"
Requires-Dist: pytest-cov>=4.0; extra == "dev"
Requires-Dist: black>=23.0; extra == "dev"
Requires-Dist: isort>=5.0; extra == "dev"
Requires-Dist: mypy>=1.0; extra == "dev"
Dynamic: license-file
